msg91_otp/__init__.py
msg91_otp/client.py
msg91_otp/country_code.py
msg91_otp/exceptions.py
msg91_otp/response.py
msg91_otp/utils.py
msg91_otp-0.1.0.dist-info/LICENSE
msg91_otp-0.1.0.dist-info/METADATA
msg91_otp-0.1.0.dist-info/WHEEL
msg91_otp-0.1.0.dist-info/top_level.txt
msg91_otp-0.1.0.dist-info/RECORD
