Metadata-Version: 2.1
Name: msg91-otp
Version: 0.1.0
Summary: Minimal OTP only API coverage for msg91.com service
Home-page: https://gitlab.com/coopon/reusable-libs/python/msg91-otp
Author: Prasanna Venkadesh
Author-email: prasanna@cooponscitech.in
License: UNKNOWN
Platform: UNKNOWN
Classifier: Programming Language :: Python :: 2.7
Classifier: Programming Language :: Python :: 3
Classifier: Programming Language :: Python :: 3.7
Classifier: Programming Language :: Python :: Implementation :: CPython
Classifier: Intended Audience :: Developers
Classifier: License :: OSI Approved :: GNU Affero General Public License v3 or later (AGPLv3+)
Classifier: Operating System :: OS Independent
Requires-Python: >=2.7
Requires-Dist: httpx (==0.7.4)
